{
  "fund_name": "Fundstrat Granny Shots US Large Cap ETF",
  "fund_ticker": "GRNY",
  "as_of_date": "2026-02-26",
  "source": "website",
  "source_url": "https://grannyshots.com/holdings/",
  "scrape_timestamp": "2026-02-26T21:33:51Z",
  "warnings": [],
  "holdings": [
    {
      "security_name": "Apple Inc.",
      "security_ticker": "AAPL",
      "shares": 385464.0,
      "portfolio_weight": 2.55,
      "market_value": 105705793.0,
      "sector": "Information Technology",
      "last_price": 272.95,
      "market_price_change": -0.47,
      "holding_key": "AAPL"
    },
    {
      "security_name": "Advanced Micro Devices",
      "security_ticker": "AMD",
      "shares": 512630.0,
      "portfolio_weight": 2.6,
      "market_value": 108093162.0,
      "sector": "Information Technology",
      "last_price": 203.32,
      "market_price_change": -3.58,
      "holding_key": "AMD"
    },
    {
      "security_name": "Amgen Inc",
      "security_ticker": "AMGN",
      "shares": 271048.0,
      "portfolio_weight": 2.51,
      "market_value": 104171878.0,
      "sector": "Health Care",
      "last_price": 378.82,
      "market_price_change": -1.43,
      "holding_key": "AMGN"
    },
    {
      "security_name": "Amazon.Com Inc",
      "security_ticker": "AMZN",
      "shares": 496680.0,
      "portfolio_weight": 2.52,
      "market_value": 104620675.0,
      "sector": "Consumer Discretionary",
      "last_price": 207.75,
      "market_price_change": -1.37,
      "holding_key": "AMZN"
    },
    {
      "security_name": "Arista Networks",
      "security_ticker": "ANET",
      "shares": 727550.0,
      "portfolio_weight": 2.33,
      "market_value": 96684120.0,
      "sector": "Information Technology",
      "last_price": 130.23,
      "market_price_change": -2.0,
      "holding_key": "ANET"
    },
    {
      "security_name": "Air Products & Chemicals, Inc.",
      "security_ticker": "APD",
      "shares": 360201.0,
      "portfolio_weight": 2.43,
      "market_value": 100964340.0,
      "sector": "Materials",
      "last_price": 275.95,
      "market_price_change": -1.55,
      "holding_key": "APD"
    },
    {
      "security_name": "Broadcom Inc. Common Stock",
      "security_ticker": "AVGO",
      "shares": 307346.0,
      "portfolio_weight": 2.46,
      "market_value": 102134149.0,
      "sector": "Information Technology",
      "last_price": 318.34,
      "market_price_change": -4.2,
      "holding_key": "AVGO"
    },
    {
      "security_name": "American Express Company",
      "security_ticker": "AXP",
      "shares": 292082.0,
      "portfolio_weight": 2.3,
      "market_value": 95537101.0,
      "sector": "Financials",
      "last_price": 334.44,
      "market_price_change": 2.25,
      "holding_key": "AXP"
    },
    {
      "security_name": "Bank of New York Mellon Corporation",
      "security_ticker": "BK",
      "shares": 841082.0,
      "portfolio_weight": 2.44,
      "market_value": 101190575.0,
      "sector": "Financials",
      "last_price": 121.61,
      "market_price_change": 1.08,
      "holding_key": "BK"
    },
    {
      "security_name": "Caterpillar Inc.",
      "security_ticker": "CAT",
      "shares": 131843.0,
      "portfolio_weight": 2.44,
      "market_value": 101072162.0,
      "sector": "Industrials",
      "last_price": 751.99,
      "market_price_change": -1.91,
      "holding_key": "CAT"
    },
    {
      "security_name": "Cadence Design Systems",
      "security_ticker": "CDNS",
      "shares": 335485.0,
      "portfolio_weight": 2.44,
      "market_value": 101262792.0,
      "sector": "Information Technology",
      "last_price": 297.6,
      "market_price_change": -1.4,
      "holding_key": "CDNS"
    },
    {
      "security_name": "Costco Wholesale Corp",
      "security_ticker": "COST",
      "shares": 100269.0,
      "portfolio_weight": 2.4,
      "market_value": 99743590.0,
      "sector": "Consumer Staples",
      "last_price": 986.28,
      "market_price_change": -0.85,
      "holding_key": "COST"
    },
    {
      "security_name": "Chevron Corporation",
      "security_ticker": "CVX",
      "shares": 554141.0,
      "portfolio_weight": 2.46,
      "market_value": 102083855.0,
      "sector": "Energy",
      "last_price": 184.6,
      "market_price_change": 0.2,
      "holding_key": "CVX"
    },
    {
      "security_name": "Deere & Company",
      "security_ticker": "DE",
      "shares": 169966.0,
      "portfolio_weight": 2.55,
      "market_value": 105992497.0,
      "sector": "Industrials",
      "last_price": 618.99,
      "market_price_change": -0.74,
      "holding_key": "DE"
    },
    {
      "security_name": "Eaton Corporation, plc Ordinary Shares",
      "security_ticker": "ETN",
      "shares": 257581.0,
      "portfolio_weight": 2.32,
      "market_value": 96214231.0,
      "sector": "Industrials",
      "last_price": 374.2,
      "market_price_change": 0.18,
      "holding_key": "ETN"
    },
    {
      "security_name": "GE Aerospace",
      "security_ticker": "GE",
      "shares": 306289.0,
      "portfolio_weight": 2.53,
      "market_value": 105023435.0,
      "sector": "Industrials",
      "last_price": 340.0,
      "market_price_change": -0.84,
      "holding_key": "GE"
    },
    {
      "security_name": "GE Vernova Inc.",
      "security_ticker": "GEV",
      "shares": 122794.0,
      "portfolio_weight": 2.59,
      "market_value": 107568772.0,
      "sector": "Industrials",
      "last_price": 874.75,
      "market_price_change": -0.14,
      "holding_key": "GEV"
    },
    {
      "security_name": "Alphabet Inc. Class A Common Stock",
      "security_ticker": "GOOGL",
      "shares": 334816.0,
      "portfolio_weight": 2.52,
      "market_value": 104763926.0,
      "sector": "Communication Services",
      "last_price": 306.81,
      "market_price_change": -1.95,
      "holding_key": "GOOGL"
    },
    {
      "security_name": "Goldman Sachs Group Inc.",
      "security_ticker": "GS",
      "shares": 106969.0,
      "portfolio_weight": 2.37,
      "market_value": 98559097.0,
      "sector": "Financials",
      "last_price": 928.0,
      "market_price_change": 0.72,
      "holding_key": "GS"
    },
    {
      "security_name": "Robinhood Markets, Inc. Class A Common Stock",
      "security_ticker": "HOOD",
      "shares": 1338117.0,
      "portfolio_weight": 2.5,
      "market_value": 103744211.0,
      "sector": "Financials",
      "last_price": 79.37,
      "market_price_change": 2.37,
      "holding_key": "HOOD"
    },
    {
      "security_name": "JPMorgan Chase & Co.",
      "security_ticker": "JPM",
      "shares": 324871.0,
      "portfolio_weight": 2.37,
      "market_value": 98533374.0,
      "sector": "Financials",
      "last_price": 303.3,
      "market_price_change": 0.0,
      "holding_key": "JPM"
    },
    {
      "security_name": "KLA Corporation Common Stock",
      "security_ticker": "KLAC",
      "shares": 68323.0,
      "portfolio_weight": 2.55,
      "market_value": 105673818.0,
      "sector": "Information Technology",
      "last_price": 1524.31,
      "market_price_change": -1.45,
      "holding_key": "KLAC"
    },
    {
      "security_name": "Meta Platforms, Inc. Class A Common Stock",
      "security_ticker": "META",
      "shares": 159823.0,
      "portfolio_weight": 2.52,
      "market_value": 104474697.0,
      "sector": "Communication Services",
      "last_price": 655.32,
      "market_price_change": 0.25,
      "holding_key": "META"
    },
    {
      "security_name": "Monster Beverage Corporation",
      "security_ticker": "MNST",
      "shares": 1226798.0,
      "portfolio_weight": 2.52,
      "market_value": 104780817.0,
      "sector": "Consumer Staples",
      "last_price": 83.01,
      "market_price_change": -2.81,
      "holding_key": "MNST"
    },
    {
      "security_name": "Microsoft Corp",
      "security_ticker": "MSFT",
      "shares": 254262.0,
      "portfolio_weight": 2.45,
      "market_value": 101857357.0,
      "sector": "Information Technology",
      "last_price": 401.05,
      "market_price_change": 0.11,
      "holding_key": "MSFT"
    },
    {
      "security_name": "MicroStrategy Inc",
      "security_ticker": "MSTR",
      "shares": 793537.0,
      "portfolio_weight": 2.59,
      "market_value": 107643294.0,
      "sector": "Information Technology",
      "last_price": 133.42,
      "market_price_change": -1.64,
      "holding_key": "MSTR"
    },
    {
      "security_name": "NetFlix Inc",
      "security_ticker": "NFLX",
      "shares": 1314675.0,
      "portfolio_weight": 2.62,
      "market_value": 108723623.0,
      "sector": "Communication Services",
      "last_price": 85.74,
      "market_price_change": 3.68,
      "holding_key": "NFLX"
    },
    {
      "security_name": "Northrop Grumman Corp.",
      "security_ticker": "NOC",
      "shares": 143970.0,
      "portfolio_weight": 2.44,
      "market_value": 101304491.0,
      "sector": "Industrials",
      "last_price": 710.9,
      "market_price_change": 1.03,
      "holding_key": "NOC"
    },
    {
      "security_name": "Nvidia Corp",
      "security_ticker": "NVDA",
      "shares": 537211.0,
      "portfolio_weight": 2.53,
      "market_value": 105056983.0,
      "sector": "Information Technology",
      "last_price": 184.76,
      "market_price_change": -5.52,
      "holding_key": "NVDA"
    },
    {
      "security_name": "Oneok, Inc.",
      "security_ticker": "OKE",
      "shares": 1172304.0,
      "portfolio_weight": 2.32,
      "market_value": 96457173.0,
      "sector": "Energy",
      "last_price": 84.02,
      "market_price_change": 2.12,
      "holding_key": "OKE"
    },
    {
      "security_name": "Packaging Corp of America",
      "security_ticker": "PKG",
      "shares": 423459.0,
      "portfolio_weight": 2.36,
      "market_value": 97785152.0,
      "sector": "Materials",
      "last_price": 231.83,
      "market_price_change": 0.39,
      "holding_key": "PKG"
    },
    {
      "security_name": "Palantir Technologies Inc. Class A Common Stock",
      "security_ticker": "PLTR",
      "shares": 729898.0,
      "portfolio_weight": 2.36,
      "market_value": 97945013.0,
      "sector": "Information Technology",
      "last_price": 137.86,
      "market_price_change": 2.73,
      "holding_key": "PLTR"
    },
    {
      "security_name": "PNC Financial Services Group",
      "security_ticker": "PNC",
      "shares": 431491.0,
      "portfolio_weight": 2.31,
      "market_value": 95769427.0,
      "sector": "Financials",
      "last_price": 222.82,
      "market_price_change": 0.39,
      "holding_key": "PNC"
    },
    {
      "security_name": "PPG Industries, Inc.",
      "security_ticker": "PPG",
      "shares": 783483.0,
      "portfolio_weight": 2.32,
      "market_value": 96462427.0,
      "sector": "Materials",
      "last_price": 123.48,
      "market_price_change": 0.29,
      "holding_key": "PPG"
    },
    {
      "security_name": "Quanta Services, Inc.",
      "security_ticker": "PWR",
      "shares": 191779.0,
      "portfolio_weight": 2.6,
      "market_value": 107927468.0,
      "sector": "Industrials",
      "last_price": 565.26,
      "market_price_change": 0.44,
      "holding_key": "PWR"
    },
    {
      "security_name": "TJX Companies, Inc. (The)",
      "security_ticker": "TJX",
      "shares": 647228.0,
      "portfolio_weight": 2.43,
      "market_value": 100851067.0,
      "sector": "Consumer Discretionary",
      "last_price": 158.69,
      "market_price_change": 1.84,
      "holding_key": "TJX"
    },
    {
      "security_name": "Texas Pacific Land Corporation",
      "security_ticker": "TPL",
      "shares": 235684.0,
      "portfolio_weight": 2.9,
      "market_value": 120269545.0,
      "sector": "Energy",
      "last_price": 511.0,
      "market_price_change": 0.14,
      "holding_key": "TPL"
    },
    {
      "security_name": "Tesla, Inc. Common Stock",
      "security_ticker": "TSLA",
      "shares": 245806.0,
      "portfolio_weight": 2.47,
      "market_value": 102599424.0,
      "sector": "Consumer Discretionary",
      "last_price": 408.1,
      "market_price_change": -2.23,
      "holding_key": "TSLA"
    },
    {
      "security_name": "Union Pacific Corp.",
      "security_ticker": "UNP",
      "shares": 386115.0,
      "portfolio_weight": 2.46,
      "market_value": 102030889.0,
      "sector": "Industrials",
      "last_price": 265.38,
      "market_price_change": 0.43,
      "holding_key": "UNP"
    },
    {
      "security_name": "Vistra Corp.",
      "security_ticker": "VST",
      "shares": 591368.0,
      "portfolio_weight": 2.5,
      "market_value": 103702292.0,
      "sector": "Utilities",
      "last_price": 176.31,
      "market_price_change": 0.54,
      "holding_key": "VST"
    }
  ]
}