{
  "fund_name": "Fundstrat Granny Shots US Large Cap ETF",
  "fund_ticker": "GRNY",
  "as_of_date": "2026-03-20",
  "source": "website",
  "source_url": "https://grannyshots.com/holdings/",
  "scrape_timestamp": "2026-03-20T20:22:28Z",
  "warnings": [],
  "holdings": [
    {
      "security_name": "Apple Inc.",
      "security_ticker": "AAPL",
      "shares": 380824.0,
      "portfolio_weight": 2.4,
      "market_value": 94809943.0,
      "sector": "Information Technology",
      "last_price": 247.99,
      "market_price_change": -0.39,
      "holding_key": "AAPL"
    },
    {
      "security_name": "Advanced Micro Devices",
      "security_ticker": "AMD",
      "shares": 506470.0,
      "portfolio_weight": 2.63,
      "market_value": 103963097.0,
      "sector": "Information Technology",
      "last_price": 201.33,
      "market_price_change": -1.92,
      "holding_key": "AMD"
    },
    {
      "security_name": "Amgen Inc",
      "security_ticker": "AMGN",
      "shares": 267768.0,
      "portfolio_weight": 2.37,
      "market_value": 93697379.0,
      "sector": "Health Care",
      "last_price": 347.8,
      "market_price_change": -0.61,
      "holding_key": "AMGN"
    },
    {
      "security_name": "Amazon.Com Inc",
      "security_ticker": "AMZN",
      "shares": 490680.0,
      "portfolio_weight": 2.59,
      "market_value": 102434357.0,
      "sector": "Consumer Discretionary",
      "last_price": 205.37,
      "market_price_change": -1.62,
      "holding_key": "AMZN"
    },
    {
      "security_name": "Arista Networks",
      "security_ticker": "ANET",
      "shares": 718750.0,
      "portfolio_weight": 2.48,
      "market_value": 97936875.0,
      "sector": "Information Technology",
      "last_price": 131.22,
      "market_price_change": -3.7,
      "holding_key": "ANET"
    },
    {
      "security_name": "Air Products & Chemicals, Inc.",
      "security_ticker": "APD",
      "shares": 355881.0,
      "portfolio_weight": 2.56,
      "market_value": 101123586.0,
      "sector": "Materials",
      "last_price": 281.01,
      "market_price_change": -1.11,
      "holding_key": "APD"
    },
    {
      "security_name": "Broadcom Inc. Common Stock",
      "security_ticker": "AVGO",
      "shares": 303666.0,
      "portfolio_weight": 2.46,
      "market_value": 97124533.0,
      "sector": "Information Technology",
      "last_price": 311.03,
      "market_price_change": -2.75,
      "holding_key": "AVGO"
    },
    {
      "security_name": "American Express Company",
      "security_ticker": "AXP",
      "shares": 288562.0,
      "portfolio_weight": 2.15,
      "market_value": 85105591.0,
      "sector": "Financials",
      "last_price": 295.5,
      "market_price_change": 0.19,
      "holding_key": "AXP"
    },
    {
      "security_name": "Bank of New York Mellon Corporation",
      "security_ticker": "BK",
      "shares": 830922.0,
      "portfolio_weight": 2.42,
      "market_value": 95472938.0,
      "sector": "Financials",
      "last_price": 114.94,
      "market_price_change": 0.03,
      "holding_key": "BK"
    },
    {
      "security_name": "Caterpillar Inc.",
      "security_ticker": "CAT",
      "shares": 130323.0,
      "portfolio_weight": 2.27,
      "market_value": 89746934.0,
      "sector": "Industrials",
      "last_price": 680.88,
      "market_price_change": -1.13,
      "holding_key": "CAT"
    },
    {
      "security_name": "Cadence Design Systems",
      "security_ticker": "CDNS",
      "shares": 331485.0,
      "portfolio_weight": 2.41,
      "market_value": 95268789.0,
      "sector": "Information Technology",
      "last_price": 283.9,
      "market_price_change": -1.22,
      "holding_key": "CDNS"
    },
    {
      "security_name": "Costco Wholesale Corp",
      "security_ticker": "COST",
      "shares": 99069.0,
      "portfolio_weight": 2.44,
      "market_value": 96570480.0,
      "sector": "Consumer Staples",
      "last_price": 972.33,
      "market_price_change": -0.25,
      "holding_key": "COST"
    },
    {
      "security_name": "Chevron Corporation",
      "security_ticker": "CVX",
      "shares": 547501.0,
      "portfolio_weight": 2.79,
      "market_value": 110288601.0,
      "sector": "Energy",
      "last_price": 201.73,
      "market_price_change": 0.14,
      "holding_key": "CVX"
    },
    {
      "security_name": "Deere & Company",
      "security_ticker": "DE",
      "shares": 167966.0,
      "portfolio_weight": 2.41,
      "market_value": 95334142.0,
      "sector": "Industrials",
      "last_price": 559.73,
      "market_price_change": -1.38,
      "holding_key": "DE"
    },
    {
      "security_name": "Eaton Corporation, plc Ordinary Shares",
      "security_ticker": "ETN",
      "shares": 254541.0,
      "portfolio_weight": 2.32,
      "market_value": 91693304.0,
      "sector": "Industrials",
      "last_price": 356.8,
      "market_price_change": -0.95,
      "holding_key": "ETN"
    },
    {
      "security_name": "GE Aerospace",
      "security_ticker": "GE",
      "shares": 302609.0,
      "portfolio_weight": 2.23,
      "market_value": 88243810.0,
      "sector": "Industrials",
      "last_price": 286.79,
      "market_price_change": -1.65,
      "holding_key": "GE"
    },
    {
      "security_name": "GE Vernova Inc.",
      "security_ticker": "GEV",
      "shares": 121354.0,
      "portfolio_weight": 2.69,
      "market_value": 106474786.0,
      "sector": "Industrials",
      "last_price": 851.07,
      "market_price_change": -3.0,
      "holding_key": "GEV"
    },
    {
      "security_name": "Alphabet Inc. Class A Common Stock",
      "security_ticker": "GOOGL",
      "shares": 330816.0,
      "portfolio_weight": 2.57,
      "market_value": 101603518.0,
      "sector": "Communication Services",
      "last_price": 301.0,
      "market_price_change": -2.0,
      "holding_key": "GOOGL"
    },
    {
      "security_name": "Goldman Sachs Group Inc.",
      "security_ticker": "GS",
      "shares": 105689.0,
      "portfolio_weight": 2.17,
      "market_value": 85555246.0,
      "sector": "Financials",
      "last_price": 813.5,
      "market_price_change": 0.49,
      "holding_key": "GS"
    },
    {
      "security_name": "Robinhood Markets, Inc. Class A Common Stock",
      "security_ticker": "HOOD",
      "shares": 1321957.0,
      "portfolio_weight": 2.48,
      "market_value": 98036331.0,
      "sector": "Financials",
      "last_price": 70.89,
      "market_price_change": -4.41,
      "holding_key": "HOOD"
    },
    {
      "security_name": "JPMorgan Chase & Co.",
      "security_ticker": "JPM",
      "shares": 320951.0,
      "portfolio_weight": 2.34,
      "market_value": 92424259.0,
      "sector": "Financials",
      "last_price": 286.56,
      "market_price_change": -0.49,
      "holding_key": "JPM"
    },
    {
      "security_name": "KLA Corporation Common Stock",
      "security_ticker": "KLAC",
      "shares": 67523.0,
      "portfolio_weight": 2.58,
      "market_value": 102062365.0,
      "sector": "Information Technology",
      "last_price": 1498.67,
      "market_price_change": -0.85,
      "holding_key": "KLAC"
    },
    {
      "security_name": "Meta Platforms, Inc. Class A Common Stock",
      "security_ticker": "META",
      "shares": 157903.0,
      "portfolio_weight": 2.42,
      "market_value": 95799750.0,
      "sector": "Communication Services",
      "last_price": 593.92,
      "market_price_change": -2.11,
      "holding_key": "META"
    },
    {
      "security_name": "Monster Beverage Corporation",
      "security_ticker": "MNST",
      "shares": 1211998.0,
      "portfolio_weight": 2.26,
      "market_value": 89372733.0,
      "sector": "Consumer Staples",
      "last_price": 73.69,
      "market_price_change": -0.07,
      "holding_key": "MNST"
    },
    {
      "security_name": "Microsoft Corp",
      "security_ticker": "MSFT",
      "shares": 251222.0,
      "portfolio_weight": 2.47,
      "market_value": 97730382.0,
      "sector": "Information Technology",
      "last_price": 382.04,
      "market_price_change": -1.79,
      "holding_key": "MSFT"
    },
    {
      "security_name": "MicroStrategy Inc",
      "security_ticker": "MSTR",
      "shares": 783937.0,
      "portfolio_weight": 2.74,
      "market_value": 108371451.0,
      "sector": "Information Technology",
      "last_price": 135.67,
      "market_price_change": -1.86,
      "holding_key": "MSTR"
    },
    {
      "security_name": "NetFlix Inc",
      "security_ticker": "NFLX",
      "shares": 1298835.0,
      "portfolio_weight": 3.02,
      "market_value": 119155123.0,
      "sector": "Communication Services",
      "last_price": 91.82,
      "market_price_change": 0.09,
      "holding_key": "NFLX"
    },
    {
      "security_name": "Northrop Grumman Corp.",
      "security_ticker": "NOC",
      "shares": 142290.0,
      "portfolio_weight": 2.57,
      "market_value": 101616404.0,
      "sector": "Industrials",
      "last_price": 706.95,
      "market_price_change": -1.01,
      "holding_key": "NOC"
    },
    {
      "security_name": "Nvidia Corp",
      "security_ticker": "NVDA",
      "shares": 530731.0,
      "portfolio_weight": 2.4,
      "market_value": 94767327.0,
      "sector": "Information Technology",
      "last_price": 173.11,
      "market_price_change": -3.05,
      "holding_key": "NVDA"
    },
    {
      "security_name": "Oneok, Inc.",
      "security_ticker": "OKE",
      "shares": 1158144.0,
      "portfolio_weight": 2.59,
      "market_value": 102368348.0,
      "sector": "Energy",
      "last_price": 89.21,
      "market_price_change": 0.93,
      "holding_key": "OKE"
    },
    {
      "security_name": "Packaging Corp of America",
      "security_ticker": "PKG",
      "shares": 418339.0,
      "portfolio_weight": 2.16,
      "market_value": 85504308.0,
      "sector": "Materials",
      "last_price": 202.73,
      "market_price_change": -0.81,
      "holding_key": "PKG"
    },
    {
      "security_name": "Palantir Technologies Inc. Class A Common Stock",
      "security_ticker": "PLTR",
      "shares": 721098.0,
      "portfolio_weight": 2.84,
      "market_value": 112260537.0,
      "sector": "Information Technology",
      "last_price": 150.68,
      "market_price_change": -3.21,
      "holding_key": "PLTR"
    },
    {
      "security_name": "PNC Financial Services Group",
      "security_ticker": "PNC",
      "shares": 426291.0,
      "portfolio_weight": 2.18,
      "market_value": 86132097.0,
      "sector": "Financials",
      "last_price": 201.71,
      "market_price_change": -0.17,
      "holding_key": "PNC"
    },
    {
      "security_name": "PPG Industries, Inc.",
      "security_ticker": "PPG",
      "shares": 774043.0,
      "portfolio_weight": 1.93,
      "market_value": 76150350.0,
      "sector": "Materials",
      "last_price": 97.22,
      "market_price_change": -1.18,
      "holding_key": "PPG"
    },
    {
      "security_name": "Quanta Services, Inc.",
      "security_ticker": "PWR",
      "shares": 189459.0,
      "portfolio_weight": 2.77,
      "market_value": 109497829.0,
      "sector": "Industrials",
      "last_price": 555.39,
      "market_price_change": -3.9,
      "holding_key": "PWR"
    },
    {
      "security_name": "TJX Companies, Inc. (The)",
      "security_ticker": "TJX",
      "shares": 639468.0,
      "portfolio_weight": 2.5,
      "market_value": 98912910.0,
      "sector": "Consumer Discretionary",
      "last_price": 154.99,
      "market_price_change": 0.2,
      "holding_key": "TJX"
    },
    {
      "security_name": "Texas Pacific Land Corporation",
      "security_ticker": "TPL",
      "shares": 232884.0,
      "portfolio_weight": 3.14,
      "market_value": 124015388.0,
      "sector": "Energy",
      "last_price": 519.41,
      "market_price_change": -2.46,
      "holding_key": "TPL"
    },
    {
      "security_name": "Tesla, Inc. Common Stock",
      "security_ticker": "TSLA",
      "shares": 242846.0,
      "portfolio_weight": 2.34,
      "market_value": 92354334.0,
      "sector": "Consumer Discretionary",
      "last_price": 368.63,
      "market_price_change": -3.07,
      "holding_key": "TSLA"
    },
    {
      "security_name": "Union Pacific Corp.",
      "security_ticker": "UNP",
      "shares": 381475.0,
      "portfolio_weight": 2.26,
      "market_value": 89333816.0,
      "sector": "Industrials",
      "last_price": 234.92,
      "market_price_change": 0.32,
      "holding_key": "UNP"
    },
    {
      "security_name": "Vistra Corp.",
      "security_ticker": "VST",
      "shares": 584248.0,
      "portfolio_weight": 2.47,
      "market_value": 97652379.0,
      "sector": "Utilities",
      "last_price": 146.02,
      "market_price_change": -12.76,
      "holding_key": "VST"
    }
  ]
}